{
  "generated_at": "2026-04-01T06:39:38.800758+08:00",
  "total_titles_processed": 594,
  "failed_sources": [],
  "trends": [
    {
      "keyword_group": "iG S赛 英雄联盟 T1",
      "match_count": 2,
      "titles": [
        {
          "title": "澳大利亚3月AIG/PWC制造业表现指数 -27.9，前值-15.6。",
          "url": "https://flash.jin10.com/detail/20260401060121394800",
          "source": "金十数据",
          "ranks": [
            13
          ],
          "is_new": true,
          "appearance_count": 1,
          "time_info": "06时39分"
        },
        {
          "title": "澳大利亚3月AIG建筑业表现指数 -31.4，前值-8.2。",
          "url": "https://flash.jin10.com/detail/20260401060044293800",
          "source": "金十数据",
          "ranks": [
            16
          ],
          "is_new": true,
          "appearance_count": 1,
          "time_info": "06时39分"
        }
      ]
    }
  ],
  "report_image_url": "https://github.com/Mirape/TrendRadar/img/news.jpg"
}