{
  "generated_at": "2026-01-26T05:24:20.310306+08:00",
  "total_titles_processed": 404,
  "failed_sources": [],
  "trends": [
    {
      "keyword_group": "iG S赛 英雄联盟 T1",
      "match_count": 3,
      "titles": [
        {
          "title": "吊车尾之战,TES复仇IG",
          "url": "https://tieba.baidu.com/hottopic/browse/hottopic?topic_id=28349648&amp;topic_name=%E5%90%8A%E8%BD%A6%E5%B0%BE%E4%B9%8B%E6%88%98%2CTES%E5%A4%8D%E4%BB%87IG",
          "source": "贴吧",
          "ranks": [
            2
          ],
          "is_new": false,
          "appearance_count": 8,
          "time_info": "[00时31分 ~ 05时24分]"
        },
        {
          "title": "TES零封IG",
          "url": "https://search.bilibili.com/all?keyword=TES%20IG",
          "source": "bilibili 热搜",
          "ranks": [
            7
          ],
          "is_new": false,
          "appearance_count": 8,
          "time_info": "[00时31分 ~ 05时24分]"
        },
        {
          "title": "T1战胜BFX取得四连胜",
          "url": "https://search.bilibili.com/all?keyword=T1%E6%88%98%E8%83%9CBFX%E5%8F%96%E5%BE%97%E5%9B%9B%E8%BF%9E%E8%83%9C",
          "source": "bilibili 热搜",
          "ranks": [
            28,
            30,
            27
          ],
          "is_new": false,
          "appearance_count": 4,
          "time_info": "[03时21分 ~ 05时24分]"
        }
      ]
    }
  ],
  "report_image_url": "https://github.com/Mirape/TrendRadar/img/news.jpg"
}