{
  "generated_at": "2026-06-30T20:13:26.537049+08:00",
  "total_titles_processed": 1187,
  "failed_sources": [],
  "trends": [
    {
      "keyword_group": "iG S赛 英雄联盟 T1",
      "match_count": 5,
      "titles": [
        {
          "title": "韩援报国,T1喜提MSI首胜",
          "url": "https://tieba.baidu.com/hottopic/browse/hottopic?topic_id=28355707&amp;topic_name=%E9%9F%A9%E6%8F%B4%E6%8A%A5%E5%9B%BD%2CT1%E5%96%9C%E6%8F%90MSI%E9%A6%96%E8%83%9C",
          "source": "贴吧",
          "ranks": [
            20,
            21,
            22,
            26
          ],
          "is_new": false,
          "appearance_count": 6,
          "time_info": "[01时41分 ~ 13时08分]"
        },
        {
          "title": "T1 3-0 KC赛后数据",
          "url": "https://search.bilibili.com/all?keyword=T1%203-0%20KC%E8%B5%9B%E5%90%8E%E6%95%B0%E6%8D%AE",
          "source": "bilibili 热搜",
          "ranks": [
            21,
            22,
            24
          ],
          "is_new": false,
          "appearance_count": 3,
          "time_info": "[06时12分 ~ 13时08分]"
        },
        {
          "title": "T1零封KC MSI",
          "url": "https://search.bilibili.com/all?keyword=T1%20KC",
          "source": "bilibili 热搜",
          "ranks": [
            12,
            17
          ],
          "is_new": false,
          "appearance_count": 2,
          "time_info": "[06时12分 ~ 08时09分]"
        },
        {
          "title": "Digital Realty 拟以35亿美元收购黑石在三座数据中心持有的股权",
          "url": "https://wallstreetcn.com/livenews/3126311",
          "source": "华尔街见闻-快讯",
          "ranks": [
            10
          ],
          "is_new": false,
          "appearance_count": 1,
          "time_info": "06时12分"
        },
        {
          "title": "锐评T1战胜KC",
          "url": "https://search.bilibili.com/all?keyword=%E9%94%90%E8%AF%84T1%E6%88%98%E8%83%9CKC",
          "source": "bilibili 热搜",
          "ranks": [
            26
          ],
          "is_new": false,
          "appearance_count": 1,
          "time_info": "13时08分"
        }
      ]
    }
  ],
  "report_image_url": "https://github.com/Mirape/TrendRadar/img/news.jpg"
}