{
  "generated_at": "2026-03-12T13:55:42.949571+08:00",
  "total_titles_processed": 1102,
  "failed_sources": [],
  "trends": [
    {
      "keyword_group": "iG S赛 英雄联盟 T1",
      "match_count": 4,
      "titles": [
        {
          "title": "中国成功研发世界最强 T1200 级超高强度碳纤维并实现百吨级量产，这对我国有何意义？",
          "url": "https://www.zhihu.com/question/2014993230404531730",
          "source": "知乎",
          "ranks": [
            13,
            8,
            7,
            5,
            4,
            2,
            1
          ],
          "is_new": false,
          "appearance_count": 10,
          "time_info": "[01时54分 ~ 13时55分]"
        },
        {
          "title": "英雄联盟16.6版本有何改动",
          "url": "https://search.bilibili.com/all?keyword=%E8%8B%B1%E9%9B%84%E8%81%94%E7%9B%9F16.6%E7%89%88%E6%9C%AC%E6%9C%89%E4%BD%95%E6%94%B9%E5%8A%A8",
          "source": "bilibili 热搜",
          "ranks": [
            16,
            18,
            29,
            24,
            21,
            19,
            20
          ],
          "is_new": false,
          "appearance_count": 9,
          "time_info": "[00时58分 ~ 13时55分]"
        },
        {
          "title": "美国能源部长Wright：希望未来数周看到货轮通航霍尔木兹海峡。",
          "url": "https://wallstreetcn.com/livenews/3068382",
          "source": "华尔街见闻-快讯",
          "ranks": [
            3
          ],
          "is_new": false,
          "appearance_count": 1,
          "time_info": "07时32分"
        },
        {
          "title": "马斯克：Digital Optimus（也称Macrohard）是xAI一特斯拉的一个联合项目。 这也是双方投资协议的一部分。",
          "url": "https://wallstreetcn.com/livenews/3068208",
          "source": "华尔街见闻-快讯",
          "ranks": [
            25
          ],
          "is_new": false,
          "appearance_count": 1,
          "time_info": "00时58分"
        }
      ]
    }
  ],
  "report_image_url": "https://github.com/Mirape/TrendRadar/img/news.jpg"
}